pydobot/__init__.py
pydobot/dobot.py
pydobot/kinematics.py
pydobot/m1_fk.py
pydobot/m1_ik.py
pydobot/message.py
pydobot/tools.py
pydobot2-0.1.0.dist-info/LICENSE.txt
pydobot2-0.1.0.dist-info/METADATA
pydobot2-0.1.0.dist-info/WHEEL
pydobot2-0.1.0.dist-info/top_level.txt
pydobot2-0.1.0.dist-info/RECORD
