Metadata-Version: 2.1
Name: pydobot2
Version: 0.1.0
Summary: Python library for Dobot Magician
Home-page: https://github.com/zdenekm/pydobot
Author: Zdenek Materna
Author-email: imaterna@fit.vut.cz
License: UNKNOWN
Keywords: dobot,magician,robotics,m1
Platform: UNKNOWN
Requires-Dist: pyserial (==3.4)
